pygmi/__init__.py
pygmi/__main__.py
pygmi/pygmi.py
pygmi_get-0.17.7.data/scripts/pygmi.py
pygmi_get-0.17.7.dist-info/METADATA
pygmi_get-0.17.7.dist-info/WHEEL
pygmi_get-0.17.7.dist-info/entry_points.txt
pygmi_get-0.17.7.dist-info/top_level.txt
pygmi_get-0.17.7.dist-info/RECORD
