Metadata-Version: 2.1
Name: pygmi-get
Version: 0.17.7
Summary: A simple package installer for Python that eliminates the need for venvs.
Home-page: https://github.com/AquaQuokka/pygmi-get
Author: AquaQuokka
License: BSD-3-Clause
Requires-Dist: click
